briff/__init__.py
briff/briff_multiviews.py
briff/briff_pairwise.py
briff/flames.py
briff/icp.py
briff/jrmpc.py
briff/pcd_utils.py
briff/so3.py
briff-0.1.1.dist-info/METADATA
briff-0.1.1.dist-info/WHEEL
briff-0.1.1.dist-info/top_level.txt
briff-0.1.1.dist-info/RECORD
