Metadata-Version: 2.1
Name: briff
Version: 0.1.1
Summary: Implementation of BRIFF & FLAMES algorithms, for Fast & Global Point Cloud rigid registration.
Author: PCR Research
Project-URL: Repository, https://github.com/pcrresearch/BRIFF.git
Classifier: Programming Language :: Python :: 3
Classifier: License :: OSI Approved :: MIT License
Classifier: Operating System :: OS Independent
Requires-Python: >=3.7
Requires-Dist: numpy
Requires-Dist: tqdm
Requires-Dist: jrmpc
Requires-Dist: torch
Requires-Dist: nvidia-ml-py3
Requires-Dist: typing-extensions ; python_version < "3.10"
